grc/__init__.py
grc/version.py
grc/scripts/__init__.py
grc/scripts/grc.py
home/exhuma/.grc/conf.d/apache_access.yml
home/exhuma/.grc/conf.d/aptitude.yml
home/exhuma/.grc/conf.d/pysetup.yml
grc-1.0.0.post3.dist-info/METADATA
grc-1.0.0.post3.dist-info/WHEEL
grc-1.0.0.post3.dist-info/entry_points.txt
grc-1.0.0.post3.dist-info/top_level.txt
grc-1.0.0.post3.dist-info/RECORD
