Metadata-Version: 2.1
Name: grc
Version: 1.0.0.post3
Summary: Generic Coloriser
Home-page: UNKNOWN
Author: Michel Albert
Author-email: michel@albert.lu
License: GPL
Platform: UNKNOWN
Requires-Dist: blessings
Requires-Dist: pexpect
Requires-Dist: pyyaml
Requires-Dist: strec
